goray/__init__.py
goray/actor.py
goray/actor_wrappers.py
goray/cli.py
goray/common.py
goray/go2py.py
goray/handlers.py
goray/object.py
goray/py2go.py
goray/registry.py
goray/state.py
goray/task.py
goray-1.2.1.dist-info/licenses/LICENSE
gorayffi/__init__.py
gorayffi/actor.py
gorayffi/cmds.py
gorayffi/consts.py
gorayffi/ffi.py
gorayffi/funccall.py
gorayffi/handlers.py
gorayffi/utils.py
goray-1.2.1.dist-info/METADATA
goray-1.2.1.dist-info/WHEEL
goray-1.2.1.dist-info/entry_points.txt
goray-1.2.1.dist-info/top_level.txt
goray-1.2.1.dist-info/RECORD
