Metadata-Version: 2.4
Name: goray
Version: 1.2.1
Summary: Python driver for GoRay project
Author-email: WeiminWang <wang0.618@qq.com>
Project-URL: Homepage, https://github.com/ray4go/go-ray
License-File: LICENSE
Requires-Dist: msgpack
Provides-Extra: ray
Requires-Dist: ray[default]; extra == "ray"
Provides-Extra: docs
Requires-Dist: mkdocs-material>=9.0.0; extra == "docs"
Requires-Dist: mkdocstrings[python]>=0.24.0; extra == "docs"
Dynamic: license-file
